hwhpykit/__init__.py
hwhpykit/connection/__init__.py
hwhpykit/connection/mqtt/__init__.py
hwhpykit/connection/mqtt/client.py
hwhpykit-1.1.8.dist-info/LICENSE
hwhpykit-1.1.8.dist-info/METADATA
hwhpykit-1.1.8.dist-info/WHEEL
hwhpykit-1.1.8.dist-info/top_level.txt
hwhpykit-1.1.8.dist-info/RECORD
