Metadata-Version: 2.1
Name: hwhpykit
Version: 1.1.8
Summary: Packaging tools for own use
Home-page: 
Author: louishwh
Author-email: louishwh@gmail.com
Classifier: Programming Language :: Python :: 3
Classifier: License :: OSI Approved :: MIT License
Classifier: Operating System :: OS Independent
Requires-Python: >=3.10
License-File: LICENSE
Requires-Dist: paho-mqtt>=2.0.0
